gphotos_sync/BadIds.py
gphotos_sync/BaseMedia.py
gphotos_sync/Checks.py
gphotos_sync/DatabaseMedia.py
gphotos_sync/DbRow.py
gphotos_sync/GoogleAlbumMedia.py
gphotos_sync/GoogleAlbumsRow.py
gphotos_sync/GoogleAlbumsSync.py
gphotos_sync/GooglePhotosDownload.py
gphotos_sync/GooglePhotosIndex.py
gphotos_sync/GooglePhotosMedia.py
gphotos_sync/GooglePhotosRow.py
gphotos_sync/LocalData.py
gphotos_sync/LocalFilesMedia.py
gphotos_sync/LocalFilesRow.py
gphotos_sync/LocalFilesScan.py
gphotos_sync/Logging.py
gphotos_sync/Queries.py
gphotos_sync/Settings.py
gphotos_sync/Utils.py
gphotos_sync/__init__.py
gphotos_sync/__main__.py
gphotos_sync/_version.py
gphotos_sync/authorize.py
gphotos_sync/restclient.py
gphotos_sync/sql/console.sql
gphotos_sync/sql/gphotos_create.sql
gphotos_sync-3.2.5.dist-info/AUTHORS
gphotos_sync-3.2.5.dist-info/LICENSE
gphotos_sync-3.2.5.dist-info/METADATA
gphotos_sync-3.2.5.dist-info/WHEEL
gphotos_sync-3.2.5.dist-info/entry_points.txt
gphotos_sync-3.2.5.dist-info/top_level.txt
gphotos_sync-3.2.5.dist-info/RECORD
